pytest_tui_runner/__init__.py
pytest_tui_runner/cli.py
pytest_tui_runner/config.py
pytest_tui_runner/hooks.py
pytest_tui_runner/logging.py
pytest_tui_runner/paths.py
pytest_tui_runner/ui/tui/app.py
pytest_tui_runner/ui/tui/handlers/button_handler.py
pytest_tui_runner/ui/tui/handlers/special_test_group.py
pytest_tui_runner/ui/tui/handlers/special_test_group_old.py
pytest_tui_runner/ui/tui/pages/terminal_view.py
pytest_tui_runner/ui/tui/pages/tests_view.py
pytest_tui_runner/ui/tui/styles/tests_view.css
pytest_tui_runner/utils/config.py
pytest_tui_runner/utils/test_results.py
pytest_tui_runner/utils/pytest/arguments.py
pytest_tui_runner/utils/pytest/encoding.py
pytest_tui_runner/utils/types/config.py
pytest_tui_runner/utils/types/config_validator.py
pytest_tui_runner/utils/types/saved_state.py
pytest_tui_runner/utils/types/widgets.py
pytest_tui_runner/utils/widgets/buttons.py
pytest_tui_runner/utils/widgets/composer.py
pytest_tui_runner/utils/widgets/manager.py
pytest_tui_runner/utils/widgets/marking.py
pytest_tui_runner/utils/widgets/state_manager.py
pytest_tui_runner/utils/widgets/widget_generator.py
pytest_tui_runner-1.0.13.dist-info/licenses/LICENSE
pytest_tui_runner-1.0.13.dist-info/METADATA
pytest_tui_runner-1.0.13.dist-info/WHEEL
pytest_tui_runner-1.0.13.dist-info/entry_points.txt
pytest_tui_runner-1.0.13.dist-info/top_level.txt
pytest_tui_runner-1.0.13.dist-info/RECORD
