Metadata-Version: 2.4
Name: pytest-tui-runner
Version: 1.0.13
Summary: Textual-based terminal UI for running pytest tests
Author-email: Jan Málek <176jenda@gmail.com>
License-Expression: MIT
Project-URL: Repository, https://github.com/JanMalek03/pytest-tui-runner
Keywords: pytest,gui,tui,plugin
Classifier: Programming Language :: Python :: 3
Classifier: Framework :: Pytest
Requires-Python: <3.14,>=3.10
License-File: LICENSE
Requires-Dist: click<=8.3.0,>=8.0.0
Requires-Dist: loguru<=0.7.3,>=0.6.0
Requires-Dist: pydantic<=2.12.4,>=2.8.0
Requires-Dist: pytest<=9.0.1,>=7.4
Requires-Dist: pytest-json-report<2.0.0,>=1.5.0
Requires-Dist: pyyaml<=6.0.3,>=5.1.0
Requires-Dist: textual<=5.3.0,>=3.0.0
Dynamic: license-file
